DESCRIPTION.rst
LICENSE
MANIFEST.in
setup.cfg
setup.py
onedrivesdk.egg-info/PKG-INFO
onedrivesdk.egg-info/SOURCES.txt
onedrivesdk.egg-info/dependency_links.txt
onedrivesdk.egg-info/requires.txt
onedrivesdk.egg-info/top_level.txt
src/onedrivesdk/__init__.py
src/onedrivesdk/async_operation_monitor.py
src/onedrivesdk/auth_provider.py
src/onedrivesdk/auth_provider_base.py
src/onedrivesdk/collection_base.py
src/onedrivesdk/error.py
src/onedrivesdk/http_provider.py
src/onedrivesdk/http_provider_base.py
src/onedrivesdk/http_response.py
src/onedrivesdk/one_drive_object_base.py
src/onedrivesdk/options.py
src/onedrivesdk/request_base.py
src/onedrivesdk/request_builder_base.py
src/onedrivesdk/session.py
src/onedrivesdk/session_base.py
src/onedrivesdk/version.py
src/onedrivesdk/version.txt
src/onedrivesdk/extensions/__init__.py
src/onedrivesdk/extensions/drive_request_builder_helper.py
src/onedrivesdk/extensions/one_drive_client_helper.py
src/onedrivesdk/extensions/onedrivesdk_helper.py
src/onedrivesdk/helpers/GetAuthCodeServer.py
src/onedrivesdk/helpers/__init__.py
src/onedrivesdk/helpers/file_slice.py
src/onedrivesdk/helpers/get_access_token_server.py
src/onedrivesdk/helpers/http_provider_with_proxy.py
src/onedrivesdk/helpers/resource_discovery.py
src/onedrivesdk/model/__init__.py
src/onedrivesdk/model/async_operation_status.py
src/onedrivesdk/model/audio.py
src/onedrivesdk/model/children_collection_page.py
src/onedrivesdk/model/chunked_upload_session_descriptor.py
src/onedrivesdk/model/deleted.py
src/onedrivesdk/model/drive.py
src/onedrivesdk/model/drives_collection_page.py
src/onedrivesdk/model/file.py
src/onedrivesdk/model/file_system_info.py
src/onedrivesdk/model/folder.py
src/onedrivesdk/model/hashes.py
src/onedrivesdk/model/identity.py
src/onedrivesdk/model/identity_set.py
src/onedrivesdk/model/image.py
src/onedrivesdk/model/item.py
src/onedrivesdk/model/item_delta_collection_page.py
src/onedrivesdk/model/item_reference.py
src/onedrivesdk/model/items_collection_page.py
src/onedrivesdk/model/location.py
src/onedrivesdk/model/open_with_app.py
src/onedrivesdk/model/open_with_set.py
src/onedrivesdk/model/permission.py
