Metadata-Version: 1.1
Name: onedrivesdk
Version: 1.1.6
Summary: Official Python OneDrive SDK for interfacing with OneDrive APIs
Home-page: http://dev.onedrive.com
Author: Microsoft
Author-email: UNKNOWN
License: MIT
Keywords: onedrive sdk microsoft
Platform: UNKNOWN
Classifier: Development Status :: 4 - Beta
Classifier: Intended Audience :: Developers
Classifier: Topic :: Software Development :: Libraries :: Python Modules
Classifier: License :: OSI Approved :: MIT License
Classifier: Programming Language :: Python :: 3.4
Classifier: Operating System :: OS Independent
Classifier: Operating System :: POSIX
Classifier: Operating System :: Microsoft :: Windows
Classifier: Operating System :: MacOS :: MacOS X
